wagtail_localize_pontoon/__init__.py
wagtail_localize_pontoon/apps.py
wagtail_localize_pontoon/git.py
wagtail_localize_pontoon/importer.py
wagtail_localize_pontoon/models.py
wagtail_localize_pontoon/pofile.py
wagtail_localize_pontoon/sync.py
wagtail_localize_pontoon/views.py
wagtail_localize_pontoon/wagtail_hooks.py
wagtail_localize_pontoon/management/__init__.py
wagtail_localize_pontoon/management/commands/__init__.py
wagtail_localize_pontoon/management/commands/submit_whole_site_to_pontoon.py
wagtail_localize_pontoon/management/commands/sync_pontoon.py
wagtail_localize_pontoon/migrations/0001_initial.py
wagtail_localize_pontoon/migrations/0001_squashed_0008_new_models.py
wagtail_localize_pontoon/migrations/0002_pontoonresourcetranslation.py
wagtail_localize_pontoon/migrations/0003_synclog.py
wagtail_localize_pontoon/migrations/0004_pontoonsynclogresource.py
wagtail_localize_pontoon/migrations/0005_auto_20190923_1405.py
wagtail_localize_pontoon/migrations/0006_auto_20191007_1700.py
wagtail_localize_pontoon/migrations/0007_delete.py
wagtail_localize_pontoon/migrations/0008_new_models.py
wagtail_localize_pontoon/migrations/__init__.py
wagtail_localize_pontoon/templates/wagtail_localize_pontoon/dashboard.html
wagtail_localize_pontoon/test/__init__.py
wagtail_localize_pontoon/test/apps.py
wagtail_localize_pontoon/test/settings.py
wagtail_localize_pontoon/test/urls.py
wagtail_localize_pontoon/test/migrations/0001_initial.py
wagtail_localize_pontoon/test/migrations/0002_auto_20191007_1608.py
wagtail_localize_pontoon/test/migrations/0003_delete_testpage.py
wagtail_localize_pontoon/test/migrations/__init__.py
wagtail_localize_pontoon/test/tests/__init__.py
wagtail_localize_pontoon/test/tests/test_auto_submit.py
wagtail_localize_pontoon/test/tests/test_git.py
wagtail_localize_pontoon/test/tests/test_importer.py
wagtail_localize_pontoon/test/tests/test_pofile_generation.py
wagtail_localize_pontoon/test/tests/test_sync.py
wagtail_localize_pontoon-0.2.1.dist-info/METADATA
wagtail_localize_pontoon-0.2.1.dist-info/WHEEL
wagtail_localize_pontoon-0.2.1.dist-info/top_level.txt
wagtail_localize_pontoon-0.2.1.dist-info/RECORD
