Metadata-Version: 2.1
Name: wagtail-localize-pontoon
Version: 0.2.1
Summary: Pontoon integration for Wagtail Localize
Home-page: UNKNOWN
Author: Karl Hobley
Author-email: karl@torchbox.com
License: BSD
Platform: UNKNOWN
Classifier: Development Status :: 3 - Alpha
Classifier: Intended Audience :: Developers
Classifier: License :: OSI Approved :: BSD License
Classifier: Operating System :: OS Independent
Classifier: Programming Language :: Python
Classifier: Programming Language :: Python :: 3
Classifier: Programming Language :: Python :: 3.4
Classifier: Programming Language :: Python :: 3.6
Classifier: Programming Language :: Python :: 3.7
Requires-Dist: wagtail-localize (<0.5,>=0.4)
Requires-Dist: polib (<2.0,>=1.1)
Requires-Dist: pygit2 (<2.0,>=1.0)
Requires-Dist: gitpython (<4.0,>=3.0)
Requires-Dist: toml (<0.11,>=0.10)
Provides-Extra: testing
Requires-Dist: dj-database-url (==0.5.0) ; extra == 'testing'
